pa/__init__.py
pa/pa.py
pa-0.0.23.dev0.dist-info/DESCRIPTION.rst
pa-0.0.23.dev0.dist-info/METADATA
pa-0.0.23.dev0.dist-info/RECORD
pa-0.0.23.dev0.dist-info/WHEEL
pa-0.0.23.dev0.dist-info/entry_points.txt
pa-0.0.23.dev0.dist-info/metadata.json
pa-0.0.23.dev0.dist-info/top_level.txt
