Metadata-Version: 2.0
Name: pa
Version: 0.0.23.dev0
Summary: Paper Arxiv: A command line based academic paper management tool.
Home-page: UNKNOWN
Author: UNKNOWN
Author-email: UNKNOWN
License: UNKNOWN
Keywords: paper arxiv manage
Platform: UNKNOWN
Classifier: Programming Language :: Python :: 2.7
Requires-Dist: html2text
Requires-Dist: lxml
